dimension_calculation/__init__.py
dimension_calculation/dimension_calculation.py
dimension_calculation-0.3.0.dist-info/METADATA
dimension_calculation-0.3.0.dist-info/WHEEL
dimension_calculation-0.3.0.dist-info/top_level.txt
dimension_calculation-0.3.0.dist-info/RECORD
