Metadata-Version: 2.4
Name: dimension-calculation
Version: 0.3.0
Summary: Calculation of the effective dimension
Author-email: Alexandre Deroux <alexandre.deroux@gmail.com>
License: MIT
Project-URL: Homepage, https://github.com/Alexandre-Deroux/Dimension-Calculation
Requires-Python: >=3.9
Requires-Dist: numpy>=1.22
Requires-Dist: pandas>=1.5
Requires-Dist: scikit-learn>=1.2
Requires-Dist: scipy>=1.8
